yolo/__init__.py
yolo/build.py
yolo/client.py
yolo/cloudformation.py
yolo/const.py
yolo/exceptions.py
yolo/faws_client.py
yolo/script.py
yolo/utils.py
yolo/waiter.py
yolo/yolo_file.py
yolo/credentials/__init__.py
yolo/credentials/aws_cli.py
yolo/dockerfiles/__init__.py
yolo/dockerfiles/python/Dockerfile
yolo/dockerfiles/python/__init__.py
yolo/services/__init__.py
yolo/services/lambda_service.py
yolo/services/s3_service.py
yolo-0.3.2.dist-info/METADATA
yolo-0.3.2.dist-info/RECORD
yolo-0.3.2.dist-info/WHEEL
yolo-0.3.2.dist-info/entry_points.txt
yolo-0.3.2.dist-info/top_level.txt
